README.md
setup.py
gltf_shapes.egg-info/PKG-INFO
gltf_shapes.egg-info/SOURCES.txt
gltf_shapes.egg-info/dependency_links.txt
gltf_shapes.egg-info/requires.txt
gltf_shapes.egg-info/top_level.txt
gltfshapes/__init__.py
gltfshapes/cube_evenly_sampled.py
gltfshapes/linear_samples.py
gltfshapes/surface.py