Metadata-Version: 2.1
Name: gltf-shapes
Version: 0.0.2
Summary: Transform numpy arrays and pandas dataframes to 3d exports
Home-page: https://github.com/emerald-geomodelling/gltf-shapes
Author: Egil Moeller
Author-email: em@emeraldgeo.no
License: UNKNOWN
Platform: UNKNOWN
